<?xml version="1.0" encoding="utf-8"?>
<customers>
  <id id="5">
    <Port>test</Port>
    <Vessel>test</Vessel>
    <Voyage>test</Voyage>
    <Departure_Date>1900-01-01T00:00:00</Departure_Date>
    <Status>test</Status>
    <VCI_Due_Date>1900-01-01T00:00:00</VCI_Due_Date>
    <Days_Overdue_VCI>test</Days_Overdue_VCI>
    <PVE_Due_Date>1900-01-01T00:00:00</PVE_Due_Date>
    <Less_Holiday>test</Less_Holiday>
    <Days_Overdue_PVE>test</Days_Overdue_PVE>
    <Notes>test</Notes>
    <Problems>test</Problems>
    <LINK_Processed>test</LINK_Processed>
    <Potential_Corrections>test</Potential_Corrections>
    <Submitted>test</Submitted>
    <Submission_Date>19000101</Submission_Date>
    <Submitted_By>test</Submitted_By>
    <DA_number>test</DA_number>
    <LinkIM_>test</LinkIM_>
    <LinkEX_>test</LinkEX_>
    <Detail>test</Detail>
    <PVE_Status_Date>test</PVE_Status_Date>
    <ID_ESTIMATE>1</ID_ESTIMATE>
    <IC_REVALIDATED>false</IC_REVALIDATED>
    <Ready_To_Process>test</Ready_To_Process>
    <TERMINAL>test</TERMINAL>
    <Double_Call>false</Double_Call>
    <VCI_Validated>1900-01-01T00:00:00</VCI_Validated>
  </id>
  <id id="1002">
    <Port>test</Port>
    <Vessel>test</Vessel>
    <Voyage>test</Voyage>
    <Departure_Date>1900-01-01T00:00:00</Departure_Date>
    <Status>test</Status>
    <VCI_Due_Date>1900-01-01T00:00:00</VCI_Due_Date>
    <Days_Overdue_VCI>test</Days_Overdue_VCI>
    <PVE_Due_Date>1900-01-01T00:00:00</PVE_Due_Date>
    <Less_Holiday>test</Less_Holiday>
    <Days_Overdue_PVE>test</Days_Overdue_PVE>
    <Notes>test</Notes>
    <Problems>test</Problems>
    <LINK_Processed>test</LINK_Processed>
    <Potential_Corrections>test</Potential_Corrections>
    <Submitted>test</Submitted>
    <Submission_Date>19000101</Submission_Date>
    <Submitted_By>test</Submitted_By>
    <DA_number>test</DA_number>
    <LinkIM_>test</LinkIM_>
    <LinkEX_>test</LinkEX_>
    <Detail>test</Detail>
    <PVE_Status_Date>test</PVE_Status_Date>
    <ID_ESTIMATE>1</ID_ESTIMATE>
    <IC_REVALIDATED>false</IC_REVALIDATED>
    <Ready_To_Process>test</Ready_To_Process>
    <TERMINAL>test</TERMINAL>
    <Double_Call>false</Double_Call>
    <VCI_Validated>1900-01-01T00:00:00</VCI_Validated>
  </id>
  <id id="1003">
    <Port>test</Port>
    <Vessel>test</Vessel>
    <Voyage>test</Voyage>
    <Departure_Date>1900-01-01T00:00:00</Departure_Date>
    <Status>test</Status>
    <VCI_Due_Date>1900-01-01T00:00:00</VCI_Due_Date>
    <Days_Overdue_VCI>test</Days_Overdue_VCI>
    <PVE_Due_Date>1900-01-01T00:00:00</PVE_Due_Date>
    <Less_Holiday>test</Less_Holiday>
    <Days_Overdue_PVE>test</Days_Overdue_PVE>
    <Notes>test</Notes>
    <Problems>test</Problems>
    <LINK_Processed>test</LINK_Processed>
    <Potential_Corrections>test</Potential_Corrections>
    <Submitted>test</Submitted>
    <Submission_Date>19000101</Submission_Date>
    <Submitted_By>test</Submitted_By>
    <DA_number>test</DA_number>
    <LinkIM_>test</LinkIM_>
    <LinkEX_>test</LinkEX_>
    <Detail>test</Detail>
    <PVE_Status_Date>test</PVE_Status_Date>
    <ID_ESTIMATE>1</ID_ESTIMATE>
    <IC_REVALIDATED>false</IC_REVALIDATED>
    <Ready_To_Process>test</Ready_To_Process>
    <TERMINAL>test</TERMINAL>
    <Double_Call>false</Double_Call>
    <VCI_Validated>1900-01-01T00:00:00</VCI_Validated>
  </id>
  <id id="1004">
    <Port>test</Port>
    <Vessel>test</Vessel>
    <Voyage>test</Voyage>
    <Departure_Date>1900-01-01T00:00:00</Departure_Date>
    <Status>test</Status>
    <VCI_Due_Date>1900-01-01T00:00:00</VCI_Due_Date>
    <Days_Overdue_VCI>test</Days_Overdue_VCI>
    <PVE_Due_Date>1900-01-01T00:00:00</PVE_Due_Date>
    <Less_Holiday>test</Less_Holiday>
    <Days_Overdue_PVE>test</Days_Overdue_PVE>
    <Notes>test</Notes>
    <Problems>test</Problems>
    <LINK_Processed>test</LINK_Processed>
    <Potential_Corrections>test</Potential_Corrections>
    <Submitted>test</Submitted>
    <Submission_Date>19000101</Submission_Date>
    <Submitted_By>test</Submitted_By>
    <DA_number>test</DA_number>
    <LinkIM_>test</LinkIM_>
    <LinkEX_>test</LinkEX_>
    <Detail>test</Detail>
    <PVE_Status_Date>test</PVE_Status_Date>
    <ID_ESTIMATE>1</ID_ESTIMATE>
    <IC_REVALIDATED>false</IC_REVALIDATED>
    <Ready_To_Process>test</Ready_To_Process>
    <TERMINAL>test</TERMINAL>
    <Double_Call>false</Double_Call>
    <VCI_Validated>1900-01-01T00:00:00</VCI_Validated>
  </id>
  <id id="1005">
    <Port>test</Port>
    <Vessel>test</Vessel>
    <Voyage>test</Voyage>
    <Departure_Date>1900-01-01T00:00:00</Departure_Date>
    <Status>test</Status>
    <VCI_Due_Date>1900-01-01T00:00:00</VCI_Due_Date>
    <Days_Overdue_VCI>test</Days_Overdue_VCI>
    <PVE_Due_Date>1900-01-01T00:00:00</PVE_Due_Date>
    <Less_Holiday>test</Less_Holiday>
    <Days_Overdue_PVE>test</Days_Overdue_PVE>
    <Notes>test</Notes>
    <Problems>test</Problems>
    <LINK_Processed>test</LINK_Processed>
    <Potential_Corrections>test</Potential_Corrections>
    <Submitted>test</Submitted>
    <Submission_Date>19000101</Submission_Date>
    <Submitted_By>test</Submitted_By>
    <DA_number>test</DA_number>
    <LinkIM_>test</LinkIM_>
    <LinkEX_>test</LinkEX_>
    <Detail>test</Detail>
    <PVE_Status_Date>test</PVE_Status_Date>
    <ID_ESTIMATE>1</ID_ESTIMATE>
    <IC_REVALIDATED>false</IC_REVALIDATED>
    <Ready_To_Process>test</Ready_To_Process>
    <TERMINAL>test</TERMINAL>
    <Double_Call>false</Double_Call>
    <VCI_Validated>1900-01-01T00:00:00</VCI_Validated>
  </id>
  <id id="1006">
    <Port>test</Port>
    <Vessel>test</Vessel>
    <Voyage>test</Voyage>
    <Departure_Date>1900-01-01T00:00:00</Departure_Date>
    <Status>test</Status>
    <VCI_Due_Date>1900-01-01T00:00:00</VCI_Due_Date>
    <Days_Overdue_VCI>test</Days_Overdue_VCI>
    <PVE_Due_Date>1900-01-01T00:00:00</PVE_Due_Date>
    <Less_Holiday>test</Less_Holiday>
    <Days_Overdue_PVE>test</Days_Overdue_PVE>
    <Notes>test</Notes>
    <Problems>test</Problems>
    <LINK_Processed>test</LINK_Processed>
    <Potential_Corrections>test</Potential_Corrections>
    <Submitted>test</Submitted>
    <Submission_Date>19000101</Submission_Date>
    <Submitted_By>test</Submitted_By>
    <DA_number>test</DA_number>
    <LinkIM_>test</LinkIM_>
    <LinkEX_>test</LinkEX_>
    <Detail>test</Detail>
    <PVE_Status_Date>test</PVE_Status_Date>
    <ID_ESTIMATE>1</ID_ESTIMATE>
    <IC_REVALIDATED>false</IC_REVALIDATED>
    <Ready_To_Process>test</Ready_To_Process>
    <TERMINAL>test</TERMINAL>
    <Double_Call>false</Double_Call>
    <VCI_Validated>1900-01-01T00:00:00</VCI_Validated>
  </id>
  <id id="1007">
    <Port>test</Port>
    <Vessel>test</Vessel>
    <Voyage>test</Voyage>
    <Departure_Date>1900-01-01T00:00:00</Departure_Date>
    <Status>test</Status>
    <VCI_Due_Date>1900-01-01T00:00:00</VCI_Due_Date>
    <Days_Overdue_VCI>test</Days_Overdue_VCI>
    <PVE_Due_Date>1900-01-01T00:00:00</PVE_Due_Date>
    <Less_Holiday>test</Less_Holiday>
    <Days_Overdue_PVE>test</Days_Overdue_PVE>
    <Notes>test</Notes>
    <Problems>test</Problems>
    <LINK_Processed>test</LINK_Processed>
    <Potential_Corrections>test</Potential_Corrections>
    <Submitted>test</Submitted>
    <Submission_Date>19000101</Submission_Date>
    <Submitted_By>test</Submitted_By>
    <DA_number>test</DA_number>
    <LinkIM_>test</LinkIM_>
    <LinkEX_>test</LinkEX_>
    <Detail>test</Detail>
    <PVE_Status_Date>test</PVE_Status_Date>
    <ID_ESTIMATE>1</ID_ESTIMATE>
    <IC_REVALIDATED>false</IC_REVALIDATED>
    <Ready_To_Process>test</Ready_To_Process>
    <TERMINAL>test</TERMINAL>
    <Double_Call>false</Double_Call>
    <VCI_Validated>1900-01-01T00:00:00</VCI_Validated>
  </id>
  <id id="1008">
    <Port>test</Port>
    <Vessel>test</Vessel>
    <Voyage>test</Voyage>
    <Departure_Date>1900-01-01T00:00:00</Departure_Date>
    <Status>test</Status>
    <VCI_Due_Date>1900-01-01T00:00:00</VCI_Due_Date>
    <Days_Overdue_VCI>test</Days_Overdue_VCI>
    <PVE_Due_Date>1900-01-01T00:00:00</PVE_Due_Date>
    <Less_Holiday>test</Less_Holiday>
    <Days_Overdue_PVE>test</Days_Overdue_PVE>
    <Notes>test</Notes>
    <Problems>test</Problems>
    <LINK_Processed>test</LINK_Processed>
    <Potential_Corrections>test</Potential_Corrections>
    <Submitted>test</Submitted>
    <Submission_Date>19000101</Submission_Date>
    <Submitted_By>test</Submitted_By>
    <DA_number>test</DA_number>
    <LinkIM_>test</LinkIM_>
    <LinkEX_>test</LinkEX_>
    <Detail>test</Detail>
    <PVE_Status_Date>test</PVE_Status_Date>
    <ID_ESTIMATE>1</ID_ESTIMATE>
    <IC_REVALIDATED>false</IC_REVALIDATED>
    <Ready_To_Process>test</Ready_To_Process>
    <TERMINAL>test</TERMINAL>
    <Double_Call>false</Double_Call>
    <VCI_Validated>1900-01-01T00:00:00</VCI_Validated>
  </id>
  <id id="1009">
    <Port>test</Port>
    <Vessel>test</Vessel>
    <Voyage>test</Voyage>
    <Departure_Date>1900-01-01T00:00:00</Departure_Date>
    <Status>test</Status>
    <VCI_Due_Date>1900-01-01T00:00:00</VCI_Due_Date>
    <Days_Overdue_VCI>test</Days_Overdue_VCI>
    <PVE_Due_Date>1900-01-01T00:00:00</PVE_Due_Date>
    <Less_Holiday>test</Less_Holiday>
    <Days_Overdue_PVE>test</Days_Overdue_PVE>
    <Notes>test</Notes>
    <Problems>test</Problems>
    <LINK_Processed>test</LINK_Processed>
    <Potential_Corrections>test</Potential_Corrections>
    <Submitted>test</Submitted>
    <Submission_Date>19000101</Submission_Date>
    <Submitted_By>test</Submitted_By>
    <DA_number>test</DA_number>
    <LinkIM_>test</LinkIM_>
    <LinkEX_>test</LinkEX_>
    <Detail>test</Detail>
    <PVE_Status_Date>test</PVE_Status_Date>
    <ID_ESTIMATE>1</ID_ESTIMATE>
    <IC_REVALIDATED>false</IC_REVALIDATED>
    <Ready_To_Process>test</Ready_To_Process>
    <TERMINAL>test</TERMINAL>
    <Double_Call>false</Double_Call>
    <VCI_Validated>1900-01-01T00:00:00</VCI_Validated>
  </id>
  <id id="1010">
    <Port>test</Port>
    <Vessel>test</Vessel>
    <Voyage>test</Voyage>
    <Departure_Date>1900-01-01T00:00:00</Departure_Date>
    <Status>test</Status>
    <VCI_Due_Date>1900-01-01T00:00:00</VCI_Due_Date>
    <Days_Overdue_VCI>test</Days_Overdue_VCI>
    <PVE_Due_Date>1900-01-01T00:00:00</PVE_Due_Date>
    <Less_Holiday>test</Less_Holiday>
    <Days_Overdue_PVE>test</Days_Overdue_PVE>
    <Notes>test</Notes>
    <Problems>test</Problems>
    <LINK_Processed>test</LINK_Processed>
    <Potential_Corrections>test</Potential_Corrections>
    <Submitted>test</Submitted>
    <Submission_Date>19000101</Submission_Date>
    <Submitted_By>test</Submitted_By>
    <DA_number>test</DA_number>
    <LinkIM_>test</LinkIM_>
    <LinkEX_>test</LinkEX_>
    <Detail>test</Detail>
    <PVE_Status_Date>test</PVE_Status_Date>
    <ID_ESTIMATE>1</ID_ESTIMATE>
    <IC_REVALIDATED>false</IC_REVALIDATED>
    <Ready_To_Process>test</Ready_To_Process>
    <TERMINAL>test</TERMINAL>
    <Double_Call>false</Double_Call>
    <VCI_Validated>1900-01-01T00:00:00</VCI_Validated>
  </id>
  <id id="1011">
    <Port>test</Port>
    <Vessel>test</Vessel>
    <Voyage>test</Voyage>
    <Departure_Date>1900-01-01T00:00:00</Departure_Date>
    <Status>test</Status>
    <VCI_Due_Date>1900-01-01T00:00:00</VCI_Due_Date>
    <Days_Overdue_VCI>test</Days_Overdue_VCI>
    <PVE_Due_Date>1900-01-01T00:00:00</PVE_Due_Date>
    <Less_Holiday>test</Less_Holiday>
    <Days_Overdue_PVE>test</Days_Overdue_PVE>
    <Notes>test</Notes>
    <Problems>test</Problems>
    <LINK_Processed>test</LINK_Processed>
    <Potential_Corrections>test</Potential_Corrections>
    <Submitted>test</Submitted>
    <Submission_Date>19000101</Submission_Date>
    <Submitted_By>test</Submitted_By>
    <DA_number>test</DA_number>
    <LinkIM_>test</LinkIM_>
    <LinkEX_>test</LinkEX_>
    <Detail>test</Detail>
    <PVE_Status_Date>test</PVE_Status_Date>
    <ID_ESTIMATE>1</ID_ESTIMATE>
    <IC_REVALIDATED>false</IC_REVALIDATED>
    <Ready_To_Process>test</Ready_To_Process>
    <TERMINAL>test</TERMINAL>
    <Double_Call>false</Double_Call>
    <VCI_Validated>1900-01-01T00:00:00</VCI_Validated>
  </id>
  <id id="1012">
    <Port>test</Port>
    <Vessel>test</Vessel>
    <Voyage>test</Voyage>
    <Departure_Date>1900-01-01T00:00:00</Departure_Date>
    <Status>test</Status>
    <VCI_Due_Date>1900-01-01T00:00:00</VCI_Due_Date>
    <Days_Overdue_VCI>test</Days_Overdue_VCI>
    <PVE_Due_Date>1900-01-01T00:00:00</PVE_Due_Date>
    <Less_Holiday>test</Less_Holiday>
    <Days_Overdue_PVE>test</Days_Overdue_PVE>
    <Notes>test</Notes>
    <Problems>test</Problems>
    <LINK_Processed>test</LINK_Processed>
    <Potential_Corrections>test</Potential_Corrections>
    <Submitted>test</Submitted>
    <Submission_Date>19000101</Submission_Date>
    <Submitted_By>test</Submitted_By>
    <DA_number>test</DA_number>
    <LinkIM_>test</LinkIM_>
    <LinkEX_>test</LinkEX_>
    <Detail>test</Detail>
    <PVE_Status_Date>test</PVE_Status_Date>
    <ID_ESTIMATE>1</ID_ESTIMATE>
    <IC_REVALIDATED>false</IC_REVALIDATED>
    <Ready_To_Process>test</Ready_To_Process>
    <TERMINAL>test</TERMINAL>
    <Double_Call>false</Double_Call>
    <VCI_Validated>1900-01-01T00:00:00</VCI_Validated>
  </id>
  <id id="1013">
    <Port>test</Port>
    <Vessel>test</Vessel>
    <Voyage>test</Voyage>
    <Departure_Date>1900-01-01T00:00:00</Departure_Date>
    <Status>test</Status>
    <VCI_Due_Date>1900-01-01T00:00:00</VCI_Due_Date>
    <Days_Overdue_VCI>test</Days_Overdue_VCI>
    <PVE_Due_Date>1900-01-01T00:00:00</PVE_Due_Date>
    <Less_Holiday>test</Less_Holiday>
    <Days_Overdue_PVE>test</Days_Overdue_PVE>
    <Notes>test</Notes>
    <Problems>test</Problems>
    <LINK_Processed>test</LINK_Processed>
    <Potential_Corrections>test</Potential_Corrections>
    <Submitted>test</Submitted>
    <Submission_Date>19000101</Submission_Date>
    <Submitted_By>test</Submitted_By>
    <DA_number>test</DA_number>
    <LinkIM_>test</LinkIM_>
    <LinkEX_>test</LinkEX_>
    <Detail>test</Detail>
    <PVE_Status_Date>test</PVE_Status_Date>
    <ID_ESTIMATE>1</ID_ESTIMATE>
    <IC_REVALIDATED>false</IC_REVALIDATED>
    <Ready_To_Process>test</Ready_To_Process>
    <TERMINAL>test</TERMINAL>
    <Double_Call>false</Double_Call>
    <VCI_Validated>1900-01-01T00:00:00</VCI_Validated>
  </id>
</customers>